{
    "entries": [
        {
            "accuracy": 97,
            "score": 16103,
            "difficulty": 0,
            "stars": 4,
            "fullcombo": false,
            "userName": "User-113f0d4f28"
        },
        {
            "accuracy": 95,
            "score": 15263,
            "difficulty": 0,
            "stars": 4,
            "fullcombo": false,
            "userName": "NotAProblemChild"
        },
        {
            "accuracy": 95,
            "score": 15237,
            "difficulty": 0,
            "stars": 4,
            "fullcombo": false,
            "userName": "plymouth61"
        },
        {
            "accuracy": 86,
            "score": 13250,
            "difficulty": 1,
            "stars": 2,
            "fullcombo": false,
            "userName": "Gokv Black"
        },
        {
            "accuracy": 83,
            "score": 13031,
            "difficulty": 1,
            "stars": 2,
            "fullcombo": false,
            "userName": "1Bad_Example"
        },
        {
            "accuracy": 95,
            "score": 11637,
            "difficulty": 0,
            "stars": 3,
            "fullcombo": false,
            "userName": "B3llaMort3"
        },
        {
            "accuracy": 94,
            "score": 10047,
            "difficulty": 0,
            "stars": 3,
            "fullcombo": false,
            "userName": "XXEmi_Gamer34XX"
        },
        {
            "accuracy": 76,
            "score": 8645,
            "difficulty": 1,
            "stars": 1,
            "fullcombo": false,
            "userName": "ian soldado04"
        },
        {
            "accuracy": 89,
            "score": 8613,
            "difficulty": 0,
            "stars": 2,
            "fullcombo": false,
            "userName": "Nicolelopezb"
        },
        {
            "accuracy": 90,
            "score": 8388,
            "difficulty": 0,
            "stars": 2,
            "fullcombo": false,
            "userName": "Jennabee1810"
        },
        {
            "accuracy": 84,
            "score": 6834,
            "difficulty": 0,
            "stars": 2,
            "fullcombo": false,
            "userName": "Leopalsy92"
        },
        {
            "accuracy": 86,
            "score": 5813,
            "difficulty": 0,
            "stars": 2,
            "fullcombo": false,
            "userName": "Spaniaole96"
        },
        {
            "accuracy": 75,
            "score": 5749,
            "difficulty": 0,
            "stars": 2,
            "fullcombo": false,
            "userName": "soulll_01"
        },
        {
            "accuracy": 63,
            "score": 5617,
            "difficulty": 0,
            "stars": 2,
            "fullcombo": false,
            "userName": "bigbonenfries"
        },
        {
            "accuracy": 81,
            "score": 5445,
            "difficulty": 0,
            "stars": 2,
            "fullcombo": false,
            "userName": "Mikey mouse78"
        },
        {
            "accuracy": 69,
            "score": 4307,
            "difficulty": 0,
            "stars": 1,
            "fullcombo": false,
            "userName": "MaxnLetty"
        },
        {
            "accuracy": 74,
            "score": 3899,
            "difficulty": 0,
            "stars": 1,
            "fullcombo": false,
            "userName": "[XBL] ALMIGHTYWILL269"
        },
        {
            "accuracy": 17,
            "score": 2629,
            "difficulty": 2,
            "stars": 0,
            "fullcombo": false,
            "userName": "[PSN] mimi2smooth"
        }
    ]
}