{
    "entries": [
        {
            "accuracy": 99,
            "score": 74752,
            "difficulty": 3,
            "stars": 6,
            "fullcombo": false,
            "userName": "ShadowsAreEVILL"
        },
        {
            "accuracy": 99,
            "score": 74539,
            "difficulty": 3,
            "stars": 6,
            "fullcombo": false,
            "userName": "HAR2BIT"
        },
        {
            "accuracy": 100,
            "score": 74475,
            "difficulty": 2,
            "stars": 5,
            "fullcombo": true,
            "userName": "DJ_Bear4554"
        },
        {
            "accuracy": 99,
            "score": 74469,
            "difficulty": 3,
            "stars": 6,
            "fullcombo": false,
            "userName": "Thenightowl312"
        },
        {
            "accuracy": 98,
            "score": 74432,
            "difficulty": 3,
            "stars": 6,
            "fullcombo": false,
            "userName": "SuperBacon27"
        },
        {
            "accuracy": 99,
            "score": 74291,
            "difficulty": 3,
            "stars": 6,
            "fullcombo": false,
            "userName": "pietrohk"
        },
        {
            "accuracy": 90,
            "score": 74061,
            "difficulty": 3,
            "stars": 6,
            "fullcombo": false,
            "userName": "TheGoldSpecter"
        },
        {
            "accuracy": 99,
            "score": 74003,
            "difficulty": 3,
            "stars": 6,
            "fullcombo": false,
            "userName": "ale-oops"
        },
        {
            "accuracy": 100,
            "score": 73986,
            "difficulty": 3,
            "stars": 6,
            "fullcombo": true,
            "userName": "sierra ponders"
        },
        {
            "accuracy": 100,
            "score": 73759,
            "difficulty": 3,
            "stars": 6,
            "fullcombo": true,
            "userName": "fluid ponders"
        },
        {
            "accuracy": 99,
            "score": 73716,
            "difficulty": 3,
            "stars": 6,
            "fullcombo": false,
            "userName": "FearlessKenji"
        },
        {
            "accuracy": 99,
            "score": 73605,
            "difficulty": 3,
            "stars": 6,
            "fullcombo": false,
            "userName": "[XBL] Milaa37384"
        },
        {
            "accuracy": 100,
            "score": 73489,
            "difficulty": 2,
            "stars": 5,
            "fullcombo": true,
            "userName": "kenzx00"
        },
        {
            "accuracy": 99,
            "score": 73282,
            "difficulty": 3,
            "stars": 6,
            "fullcombo": false,
            "userName": "BonziFX"
        },
        {
            "accuracy": 100,
            "score": 73206,
            "difficulty": 2,
            "stars": 5,
            "fullcombo": true,
            "userName": "Eren-Jaeger3695"
        },
        {
            "accuracy": 100,
            "score": 73158,
            "difficulty": 3,
            "stars": 6,
            "fullcombo": true,
            "userName": "topoftheℛest80"
        },
        {
            "accuracy": 98,
            "score": 73058,
            "difficulty": 3,
            "stars": 6,
            "fullcombo": false,
            "userName": "Axsphyxia"
        },
        {
            "accuracy": 100,
            "score": 72933,
            "difficulty": 3,
            "stars": 6,
            "fullcombo": true,
            "userName": "androgynuos"
        },
        {
            "accuracy": 100,
            "score": 72644,
            "difficulty": 2,
            "stars": 5,
            "fullcombo": true,
            "userName": "One.thechosen1"
        },
        {
            "accuracy": 98,
            "score": 72493,
            "difficulty": 3,
            "stars": 6,
            "fullcombo": false,
            "userName": "brk.lynღ"
        },
        {
            "accuracy": 100,
            "score": 72303,
            "difficulty": 2,
            "stars": 5,
            "fullcombo": true,
            "userName": "English_Homicide"
        },
        {
            "accuracy": 98,
            "score": 72120,
            "difficulty": 3,
            "stars": 6,
            "fullcombo": false,
            "userName": "Agent S Smith"
        },
        {
            "accuracy": 100,
            "score": 71935,
            "difficulty": 2,
            "stars": 5,
            "fullcombo": true,
            "userName": "YTFortnite0_pro1"
        },
        {
            "accuracy": 100,
            "score": 71915,
            "difficulty": 2,
            "stars": 5,
            "fullcombo": true,
            "userName": "skippy_151"
        },
        {
            "accuracy": 100,
            "score": 71871,
            "difficulty": 2,
            "stars": 5,
            "fullcombo": true,
            "userName": "ionwwedgk1675"
        },
        {
            "accuracy": 99,
            "score": 71863,
            "difficulty": 3,
            "stars": 6,
            "fullcombo": false,
            "userName": "Hollawould"
        },
        {
            "accuracy": 99,
            "score": 71825,
            "difficulty": 3,
            "stars": 6,
            "fullcombo": false,
            "userName": "Bangtan_Snake61"
        },
        {
            "accuracy": 100,
            "score": 71668,
            "difficulty": 2,
            "stars": 5,
            "fullcombo": true,
            "userName": "Tomplus7"
        },
        {
            "accuracy": 100,
            "score": 71500,
            "difficulty": 2,
            "stars": 5,
            "fullcombo": true,
            "userName": "thebooshgaming"
        },
        {
            "accuracy": 99,
            "score": 71460,
            "difficulty": 3,
            "stars": 6,
            "fullcombo": false,
            "userName": "UBoiDemo"
        },
        {
            "accuracy": 100,
            "score": 71432,
            "difficulty": 2,
            "stars": 5,
            "fullcombo": true,
            "userName": "GAViN.VV"
        },
        {
            "accuracy": 99,
            "score": 71412,
            "difficulty": 3,
            "stars": 6,
            "fullcombo": false,
            "userName": "Mc_Lovin-_-"
        },
        {
            "accuracy": 100,
            "score": 71334,
            "difficulty": 2,
            "stars": 5,
            "fullcombo": true,
            "userName": "websikat"
        },
        {
            "accuracy": 97,
            "score": 71171,
            "difficulty": 3,
            "stars": 6,
            "fullcombo": false,
            "userName": "PunkiePossum"
        },
        {
            "accuracy": 99,
            "score": 70991,
            "difficulty": 3,
            "stars": 5,
            "fullcombo": false,
            "userName": "CKiiLLA"
        },
        {
            "accuracy": 100,
            "score": 70958,
            "difficulty": 2,
            "stars": 5,
            "fullcombo": true,
            "userName": "Moonalola187"
        },
        {
            "accuracy": 100,
            "score": 70939,
            "difficulty": 2,
            "stars": 5,
            "fullcombo": true,
            "userName": "Blakeg141"
        },
        {
            "accuracy": 100,
            "score": 70590,
            "difficulty": 2,
            "stars": 5,
            "fullcombo": false,
            "userName": "vlaletiti"
        },
        {
            "accuracy": 100,
            "score": 70446,
            "difficulty": 2,
            "stars": 5,
            "fullcombo": true,
            "userName": "CulturedEar8117"
        },
        {
            "accuracy": 100,
            "score": 70272,
            "difficulty": 2,
            "stars": 5,
            "fullcombo": true,
            "userName": "ZdaBear09"
        },
        {
            "accuracy": 100,
            "score": 70219,
            "difficulty": 2,
            "stars": 5,
            "fullcombo": true,
            "userName": "innocient"
        },
        {
            "accuracy": 99,
            "score": 69664,
            "difficulty": 2,
            "stars": 5,
            "fullcombo": false,
            "userName": "El general650"
        },
        {
            "accuracy": 99,
            "score": 69638,
            "difficulty": 2,
            "stars": 5,
            "fullcombo": false,
            "userName": "lildinkys"
        },
        {
            "accuracy": 98,
            "score": 69609,
            "difficulty": 3,
            "stars": 5,
            "fullcombo": false,
            "userName": "capyn4ra"
        },
        {
            "accuracy": 98,
            "score": 69498,
            "difficulty": 3,
            "stars": 5,
            "fullcombo": false,
            "userName": "MOCAS-6-6-6"
        },
        {
            "accuracy": 99,
            "score": 69419,
            "difficulty": 3,
            "stars": 5,
            "fullcombo": false,
            "userName": "7dS LowFPS"
        },
        {
            "accuracy": 100,
            "score": 69260,
            "difficulty": 2,
            "stars": 5,
            "fullcombo": true,
            "userName": "M0IST GL1ZZY"
        },
        {
            "accuracy": 98,
            "score": 69198,
            "difficulty": 3,
            "stars": 5,
            "fullcombo": false,
            "userName": "iam.chip"
        },
        {
            "accuracy": 97,
            "score": 69020,
            "difficulty": 3,
            "stars": 5,
            "fullcombo": false,
            "userName": "FunXFT"
        },
        {
            "accuracy": 98,
            "score": 68827,
            "difficulty": 3,
            "stars": 5,
            "fullcombo": false,
            "userName": "もえぴ-67809"
        },
        {
            "accuracy": 99,
            "score": 68519,
            "difficulty": 2,
            "stars": 5,
            "fullcombo": false,
            "userName": "PurpleDiablesse"
        },
        {
            "accuracy": 98,
            "score": 68300,
            "difficulty": 3,
            "stars": 5,
            "fullcombo": false,
            "userName": "Kamozz."
        },
        {
            "accuracy": 98,
            "score": 68140,
            "difficulty": 3,
            "stars": 5,
            "fullcombo": false,
            "userName": "dmoney18robert"
        },
        {
            "accuracy": 98,
            "score": 68112,
            "difficulty": 3,
            "stars": 5,
            "fullcombo": false,
            "userName": "legacy23ㅤ"
        },
        {
            "accuracy": 99,
            "score": 67989,
            "difficulty": 3,
            "stars": 5,
            "fullcombo": false,
            "userName": "johnode"
        },
        {
            "accuracy": 98,
            "score": 67917,
            "difficulty": 3,
            "stars": 5,
            "fullcombo": false,
            "userName": "KittyLeighFarrel"
        },
        {
            "accuracy": 98,
            "score": 67805,
            "difficulty": 3,
            "stars": 5,
            "fullcombo": false,
            "userName": "PSALMS91_"
        },
        {
            "accuracy": 98,
            "score": 67689,
            "difficulty": 3,
            "stars": 5,
            "fullcombo": false,
            "userName": "Rcharbon"
        },
        {
            "accuracy": 100,
            "score": 67543,
            "difficulty": 3,
            "stars": 5,
            "fullcombo": true,
            "userName": "Killerpatches21"
        },
        {
            "accuracy": 99,
            "score": 67416,
            "difficulty": 2,
            "stars": 5,
            "fullcombo": false,
            "userName": "ChikieLove93"
        },
        {
            "accuracy": 98,
            "score": 67337,
            "difficulty": 3,
            "stars": 5,
            "fullcombo": false,
            "userName": "SkyesV"
        },
        {
            "accuracy": 98,
            "score": 67193,
            "difficulty": 2,
            "stars": 5,
            "fullcombo": false,
            "userName": "CarterSD17"
        },
        {
            "accuracy": 99,
            "score": 66951,
            "difficulty": 2,
            "stars": 5,
            "fullcombo": false,
            "userName": "Acidfireeyes"
        },
        {
            "accuracy": 99,
            "score": 66678,
            "difficulty": 3,
            "stars": 5,
            "fullcombo": false,
            "userName": "oO_Matcha_Oo"
        },
        {
            "accuracy": 98,
            "score": 66586,
            "difficulty": 3,
            "stars": 5,
            "fullcombo": false,
            "userName": "Creaming Problem"
        },
        {
            "accuracy": 98,
            "score": 66480,
            "difficulty": 3,
            "stars": 5,
            "fullcombo": false,
            "userName": "ian_castrito"
        },
        {
            "accuracy": 99,
            "score": 66274,
            "difficulty": 3,
            "stars": 5,
            "fullcombo": false,
            "userName": "Xx_Drewbie_xXTTV"
        },
        {
            "accuracy": 98,
            "score": 66260,
            "difficulty": 3,
            "stars": 5,
            "fullcombo": false,
            "userName": "Saw314"
        },
        {
            "accuracy": 97,
            "score": 65281,
            "difficulty": 3,
            "stars": 5,
            "fullcombo": false,
            "userName": "DADDI CH1ll"
        },
        {
            "accuracy": 98,
            "score": 64827,
            "difficulty": 3,
            "stars": 5,
            "fullcombo": false,
            "userName": "Metalupyour82"
        },
        {
            "accuracy": 99,
            "score": 64767,
            "difficulty": 2,
            "stars": 5,
            "fullcombo": false,
            "userName": "vgtazx"
        },
        {
            "accuracy": 99,
            "score": 64418,
            "difficulty": 2,
            "stars": 5,
            "fullcombo": false,
            "userName": "CasualBoa6580"
        },
        {
            "accuracy": 99,
            "score": 64363,
            "difficulty": 2,
            "stars": 5,
            "fullcombo": false,
            "userName": "naytorpower"
        },
        {
            "accuracy": 98,
            "score": 64137,
            "difficulty": 2,
            "stars": 5,
            "fullcombo": false,
            "userName": "ErickHdzper150"
        },
        {
            "accuracy": 97,
            "score": 63573,
            "difficulty": 2,
            "stars": 5,
            "fullcombo": false,
            "userName": "Gibosdog78"
        },
        {
            "accuracy": 99,
            "score": 63349,
            "difficulty": 3,
            "stars": 5,
            "fullcombo": false,
            "userName": "Itzhollows"
        },
        {
            "accuracy": 98,
            "score": 63230,
            "difficulty": 2,
            "stars": 5,
            "fullcombo": false,
            "userName": "Darko Gremory"
        },
        {
            "accuracy": 99,
            "score": 63081,
            "difficulty": 2,
            "stars": 5,
            "fullcombo": false,
            "userName": "Jevil77 X"
        },
        {
            "accuracy": 98,
            "score": 63033,
            "difficulty": 3,
            "stars": 5,
            "fullcombo": false,
            "userName": "UhMeowji"
        },
        {
            "accuracy": 99,
            "score": 62873,
            "difficulty": 2,
            "stars": 5,
            "fullcombo": false,
            "userName": "MercedesMonster"
        },
        {
            "accuracy": 99,
            "score": 62745,
            "difficulty": 2,
            "stars": 5,
            "fullcombo": false,
            "userName": "layschipXD"
        },
        {
            "accuracy": 97,
            "score": 62613,
            "difficulty": 2,
            "stars": 5,
            "fullcombo": false,
            "userName": "[PSN] ohms_eros"
        },
        {
            "accuracy": 97,
            "score": 62526,
            "difficulty": 3,
            "stars": 5,
            "fullcombo": false,
            "userName": "mcqueeneyL"
        },
        {
            "accuracy": 99,
            "score": 62201,
            "difficulty": 2,
            "stars": 5,
            "fullcombo": false,
            "userName": "Kelpothegod"
        },
        {
            "accuracy": 99,
            "score": 62170,
            "difficulty": 2,
            "stars": 5,
            "fullcombo": false,
            "userName": "IılMihael_MCIıl"
        },
        {
            "accuracy": 99,
            "score": 62102,
            "difficulty": 2,
            "stars": 5,
            "fullcombo": false,
            "userName": "AI23.AND7"
        },
        {
            "accuracy": 98,
            "score": 61970,
            "difficulty": 2,
            "stars": 5,
            "fullcombo": false,
            "userName": "tokki kat"
        },
        {
            "accuracy": 99,
            "score": 61801,
            "difficulty": 2,
            "stars": 5,
            "fullcombo": false,
            "userName": "ogpunkin"
        },
        {
            "accuracy": 99,
            "score": 61649,
            "difficulty": 2,
            "stars": 5,
            "fullcombo": false,
            "userName": "Juli1234566"
        },
        {
            "accuracy": 99,
            "score": 61321,
            "difficulty": 2,
            "stars": 5,
            "fullcombo": false,
            "userName": "TacticalStitch"
        },
        {
            "accuracy": 97,
            "score": 61240,
            "difficulty": 2,
            "stars": 5,
            "fullcombo": false,
            "userName": "ʚঌNaღLoveღYu໒ɞ"
        },
        {
            "accuracy": 98,
            "score": 61184,
            "difficulty": 3,
            "stars": 5,
            "fullcombo": false,
            "userName": "CrickyVambo"
        },
        {
            "accuracy": 99,
            "score": 60599,
            "difficulty": 2,
            "stars": 5,
            "fullcombo": false,
            "userName": "CanadianTaxi"
        },
        {
            "accuracy": 99,
            "score": 60427,
            "difficulty": 2,
            "stars": 5,
            "fullcombo": false,
            "userName": "mac.adellic"
        },
        {
            "accuracy": 98,
            "score": 59899,
            "difficulty": 2,
            "stars": 5,
            "fullcombo": false,
            "userName": "Riley.Crisostomo"
        },
        {
            "accuracy": 98,
            "score": 59885,
            "difficulty": 2,
            "stars": 5,
            "fullcombo": false,
            "userName": "AREN_724_ISFJ"
        },
        {
            "accuracy": 99,
            "score": 59880,
            "difficulty": 2,
            "stars": 5,
            "fullcombo": false,
            "userName": "NJRJBOIII"
        },
        {
            "accuracy": 98,
            "score": 58974,
            "difficulty": 3,
            "stars": 5,
            "fullcombo": false,
            "userName": "Whit_Titt_"
        },
        {
            "accuracy": 99,
            "score": 58938,
            "difficulty": 2,
            "stars": 5,
            "fullcombo": false,
            "userName": "D0NCR1X83"
        },
        {
            "accuracy": 96,
            "score": 58870,
            "difficulty": 3,
            "stars": 5,
            "fullcombo": false,
            "userName": "Weavesday"
        }
    ]
}