{
    "entries": [
        {
            "accuracy": 99,
            "score": 51809,
            "difficulty": 1,
            "stars": 5,
            "fullcombo": false,
            "userName": "XxPedroPlayBRxX"
        },
        {
            "accuracy": 99,
            "score": 51399,
            "difficulty": 1,
            "stars": 5,
            "fullcombo": false,
            "userName": "Lady_LatheTTV"
        },
        {
            "accuracy": 99,
            "score": 50553,
            "difficulty": 1,
            "stars": 5,
            "fullcombo": false,
            "userName": "ghostbusters195"
        },
        {
            "accuracy": 87,
            "score": 48586,
            "difficulty": 2,
            "stars": 2,
            "fullcombo": false,
            "userName": "f-OsHy"
        },
        {
            "accuracy": 98,
            "score": 47339,
            "difficulty": 1,
            "stars": 5,
            "fullcombo": false,
            "userName": "R.RaeL.3901"
        },
        {
            "accuracy": 98,
            "score": 46474,
            "difficulty": 1,
            "stars": 5,
            "fullcombo": false,
            "userName": "LeBeech1620"
        },
        {
            "accuracy": 79,
            "score": 44526,
            "difficulty": 3,
            "stars": 2,
            "fullcombo": false,
            "userName": "HuelsKG"
        },
        {
            "accuracy": 98,
            "score": 42903,
            "difficulty": 1,
            "stars": 5,
            "fullcombo": false,
            "userName": "Trovik_Lathander"
        },
        {
            "accuracy": 72,
            "score": 41592,
            "difficulty": 3,
            "stars": 2,
            "fullcombo": false,
            "userName": "Mad Jix Mako"
        },
        {
            "accuracy": 96,
            "score": 40891,
            "difficulty": 1,
            "stars": 5,
            "fullcombo": false,
            "userName": "HULLR1PPER"
        },
        {
            "accuracy": 94,
            "score": 36501,
            "difficulty": 1,
            "stars": 5,
            "fullcombo": false,
            "userName": "[PSN] l_-Lightning-_I"
        },
        {
            "accuracy": 97,
            "score": 35645,
            "difficulty": 1,
            "stars": 5,
            "fullcombo": false,
            "userName": "devon420_"
        },
        {
            "accuracy": 96,
            "score": 34702,
            "difficulty": 1,
            "stars": 5,
            "fullcombo": false,
            "userName": "Vlonejxyy"
        },
        {
            "accuracy": 92,
            "score": 26708,
            "difficulty": 1,
            "stars": 4,
            "fullcombo": false,
            "userName": "MarcosXD31"
        },
        {
            "accuracy": 85,
            "score": 20267,
            "difficulty": 1,
            "stars": 3,
            "fullcombo": false,
            "userName": "[PSN] Mucinex"
        },
        {
            "accuracy": 100,
            "score": 17819,
            "difficulty": 0,
            "stars": 5,
            "fullcombo": true,
            "userName": "Matt y solo game"
        },
        {
            "accuracy": 100,
            "score": 17084,
            "difficulty": 0,
            "stars": 5,
            "fullcombo": true,
            "userName": "Deedy Andrade"
        },
        {
            "accuracy": 100,
            "score": 16949,
            "difficulty": 0,
            "stars": 5,
            "fullcombo": true,
            "userName": "NiftyCricket9759"
        },
        {
            "accuracy": 30,
            "score": 16830,
            "difficulty": 2,
            "stars": 1,
            "fullcombo": false,
            "userName": "peyteytatey50"
        },
        {
            "accuracy": 99,
            "score": 16224,
            "difficulty": 0,
            "stars": 5,
            "fullcombo": false,
            "userName": "Rhaegal277"
        },
        {
            "accuracy": 99,
            "score": 14349,
            "difficulty": 0,
            "stars": 5,
            "fullcombo": false,
            "userName": "PHYSCOPATH_SLAYR"
        },
        {
            "accuracy": 99,
            "score": 14206,
            "difficulty": 0,
            "stars": 5,
            "fullcombo": false,
            "userName": "ExcitedMagpie690"
        },
        {
            "accuracy": 98,
            "score": 13005,
            "difficulty": 0,
            "stars": 5,
            "fullcombo": false,
            "userName": "issaamorr"
        },
        {
            "accuracy": 27,
            "score": 12055,
            "difficulty": 2,
            "stars": 1,
            "fullcombo": false,
            "userName": "goldenpotatoking"
        },
        {
            "accuracy": 97,
            "score": 11096,
            "difficulty": 0,
            "stars": 5,
            "fullcombo": false,
            "userName": "DarkSebastianGay"
        },
        {
            "accuracy": 97,
            "score": 8459,
            "difficulty": 0,
            "stars": 4,
            "fullcombo": false,
            "userName": "[XBL] NIGHTWOLF420934"
        },
        {
            "accuracy": 58,
            "score": 7136,
            "difficulty": 1,
            "stars": 1,
            "fullcombo": false,
            "userName": "GamerWolves0873"
        },
        {
            "accuracy": 91,
            "score": 7119,
            "difficulty": 0,
            "stars": 3,
            "fullcombo": false,
            "userName": "Amorae02"
        },
        {
            "accuracy": 90,
            "score": 4970,
            "difficulty": 0,
            "stars": 3,
            "fullcombo": false,
            "userName": "TrxppyHxppy200"
        },
        {
            "accuracy": 77,
            "score": 3381,
            "difficulty": 0,
            "stars": 2,
            "fullcombo": false,
            "userName": "W3LL3R1"
        },
        {
            "accuracy": 8,
            "score": 320,
            "difficulty": 0,
            "stars": 0,
            "fullcombo": false,
            "userName": "Serc_09"
        },
        {
            "accuracy": 0,
            "score": 0,
            "difficulty": 3,
            "stars": 0,
            "fullcombo": true,
            "userName": "SonicSoup1"
        }
    ]
}